hash_things/__init__.py
hash_things/hash_dict.py
hash_things-0.2.0.dist-info/DESCRIPTION.rst
hash_things-0.2.0.dist-info/METADATA
hash_things-0.2.0.dist-info/RECORD
hash_things-0.2.0.dist-info/WHEEL
hash_things-0.2.0.dist-info/metadata.json
hash_things-0.2.0.dist-info/top_level.txt
