Metadata-Version: 2.0
Name: hash-things
Version: 0.2.0
Summary: Hash all sorts of things in Python
Home-page: https://github.com/phalt/hash_things
Author: Paul Hallett
Author-email: paulandrewhallett@gmail.com
License: MIT license
Keywords: Hash dict
Platform: UNKNOWN
Classifier: Development Status :: 4 - Beta
Classifier: Intended Audience :: Developers
Classifier: License :: OSI Approved :: MIT License
Classifier: Natural Language :: English
Classifier: Programming Language :: Python :: 3.6
Classifier: Programming Language :: Python :: 3.7
